dnet.so
dnet-1.12.dist-info/DESCRIPTION.rst
dnet-1.12.dist-info/METADATA
dnet-1.12.dist-info/metadata.json
dnet-1.12.dist-info/RECORD
dnet-1.12.dist-info/top_level.txt
dnet-1.12.dist-info/WHEEL
