Metadata-Version: 2.0
Name: dnet
Version: 1.12
Summary: low-level networking library
Home-page: http://libdnet.sourceforge.net/
Author: Dug Song
Author-email: dugsong@monkey.org
License: UNKNOWN
Platform: UNKNOWN
